cinder_tempest_plugin/__init__.py
cinder_tempest_plugin/cinder_clients.py
cinder_tempest_plugin/config.py
cinder_tempest_plugin/exceptions.py
cinder_tempest_plugin/plugin.py
cinder_tempest_plugin/api/__init__.py
cinder_tempest_plugin/api/volume/__init__.py
cinder_tempest_plugin/api/volume/base.py
cinder_tempest_plugin/api/volume/test_create_from_image.py
cinder_tempest_plugin/api/volume/test_multiple_volume_from_resource.py
cinder_tempest_plugin/api/volume/test_volume_backup.py
cinder_tempest_plugin/api/volume/test_volume_dependency.py
cinder_tempest_plugin/api/volume/test_volume_revert.py
cinder_tempest_plugin/api/volume/test_volume_unicode.py
cinder_tempest_plugin/api/volume/admin/__init__.py
cinder_tempest_plugin/api/volume/admin/test_consistencygroups.py
cinder_tempest_plugin/api/volume/admin/test_volume_backup.py
cinder_tempest_plugin/common/__init__.py
cinder_tempest_plugin/common/concurrency.py
cinder_tempest_plugin/rbac/__init__.py
cinder_tempest_plugin/rbac/v3/__init__.py
cinder_tempest_plugin/rbac/v3/base.py
cinder_tempest_plugin/rbac/v3/test_backups.py
cinder_tempest_plugin/rbac/v3/test_capabilities.py
cinder_tempest_plugin/rbac/v3/test_snapshots.py
cinder_tempest_plugin/rbac/v3/test_user_messages.py
cinder_tempest_plugin/rbac/v3/test_volume_actions.py
cinder_tempest_plugin/rbac/v3/test_volume_types.py
cinder_tempest_plugin/rbac/v3/test_volumes.py
cinder_tempest_plugin/scenario/__init__.py
cinder_tempest_plugin/scenario/manager.py
cinder_tempest_plugin/scenario/test_encrypted_volume_transfer.py
cinder_tempest_plugin/scenario/test_snapshots.py
cinder_tempest_plugin/scenario/test_volume_concurrency.py
cinder_tempest_plugin/scenario/test_volume_encrypted.py
cinder_tempest_plugin/scenario/test_volume_multiattach.py
cinder_tempest_plugin/services/__init__.py
cinder_tempest_plugin/services/consistencygroups_client.py
cinder_tempest_plugin/services/volume_revert_client.py
cinder_tempest_plugin-1.20.0.dist-info/AUTHORS
cinder_tempest_plugin-1.20.0.dist-info/LICENSE
cinder_tempest_plugin-1.20.0.dist-info/METADATA
cinder_tempest_plugin-1.20.0.dist-info/WHEEL
cinder_tempest_plugin-1.20.0.dist-info/entry_points.txt
cinder_tempest_plugin-1.20.0.dist-info/pbr.json
cinder_tempest_plugin-1.20.0.dist-info/top_level.txt
cinder_tempest_plugin-1.20.0.dist-info/RECORD
